selenium_captcha_processing/__init__.py
selenium_captcha_processing/bypassing.py
selenium_captcha_processing/captcha.py
selenium_captcha_processing/classification.py
selenium_captcha_processing/config.py
selenium_captcha_processing/data.py
selenium_captcha_processing/detectors/detect_cloudflare_turnstile.py
selenium_captcha_processing/detectors/detect_cloudflare_turnstile_page.py
selenium_captcha_processing/detectors/detect_geetest_captcha.py
selenium_captcha_processing/detectors/detect_key_captcha.py
selenium_captcha_processing/detectors/detect_lemin_captcha.py
selenium_captcha_processing/detectors/detect_mt_captcha.py
selenium_captcha_processing/detectors/detect_re_captcha.py
selenium_captcha_processing/detectors/detect_unknown_image_captcha.py
selenium_captcha_processing/detectors/interfaces/detector.py
selenium_captcha_processing/factory.py
selenium_captcha_processing/helpers.py
selenium_captcha_processing/solvers/interfaces/solver.py
selenium_captcha_processing/solvers/solve_cloudflare_turnstile.py
selenium_captcha_processing/solvers/solve_re_captcha.py
selenium_captcha_processing/solving.py
selenium_captcha_processing/utils/container.py
selenium_captcha_processing/utils/interfaces/speech_recogniser.py
selenium_captcha_processing/utils/recognize_speech_by_google_api.py
selenium_captcha_processing-1.0.2.dist-info/LICENSE
selenium_captcha_processing-1.0.2.dist-info/METADATA
selenium_captcha_processing-1.0.2.dist-info/WHEEL
selenium_captcha_processing-1.0.2.dist-info/RECORD
