Metadata-Version: 2.3
Name: selenium-captcha-processing
Version: 1.0.2
Summary: A Python package for detecting and solving various captchas in Selenium-based web automation, supporting reCAPTCHA, Cloudflare Turnstile, and more.
License: MIT License
Keywords: captcha,selenium,web-automation,recaptcha,cloudflare-turnstile,geetest,speech-recognition,bypass-captcha
Author: FINWAX
Author-email: waxbid@gmail.com
Requires-Python: >=3.10
Classifier: Development Status :: 5 - Production/Stable
Classifier: Intended Audience :: Developers
Classifier: License :: OSI Approved :: MIT License
Classifier: Programming Language :: Python :: 3
Classifier: Programming Language :: Python :: 3.10
Classifier: Programming Language :: Python :: 3.11
Classifier: Programming Language :: Python :: 3.12
Classifier: Topic :: Software Development :: Libraries :: Python Modules
Classifier: Topic :: Internet :: WWW/HTTP :: Browsers
Classifier: Operating System :: OS Independent
Requires-Dist: pydub (>=0.25.1,<0.26.0)
Requires-Dist: requests (>=2.32.4,<3.0.0)
Requires-Dist: selenium (>=4.33.0,<5.0.0)
Requires-Dist: selmate (>=1.1.0,<2.0.0)
Requires-Dist: speechrecognition (>=3.14.3,<4.0.0)
Project-URL: Homepage, https://github.com/FINWAX/selenium-captcha-processing.py
Project-URL: Repository, https://github.com/FINWAX/selenium-captcha-processing.py
